djangoloco/__init__.py
djangoloco/admin.py
djangoloco/apps.py
djangoloco/models.py
djangoloco/tests.py
djangoloco/views.py
djangoloco/management/commands/loco.py
djangoloco/migrations/__init__.py
djangoloco-1.1.0.dist-info/LICENSE
djangoloco-1.1.0.dist-info/METADATA
djangoloco-1.1.0.dist-info/WHEEL
djangoloco-1.1.0.dist-info/top_level.txt
djangoloco-1.1.0.dist-info/RECORD
